Metadata-Version: 2.4
Name: llm-tools-searxng
Version: 0.1.1
Summary: A tool to search the web using SearXNG.
Author: Justyn Shull
License-Expression: Apache-2.0
Project-URL: Homepage, https://github.com/justyns/llm-tools-searxng
Project-URL: Changelog, https://github.com/justyns/llm-tools-searxng/releases
Project-URL: Issues, https://github.com/justyns/llm-tools-searxng/issues
Project-URL: CI, https://github.com/justyns/llm-tools-searxng/actions
Requires-Python: >=3.9
License-File: LICENSE
Requires-Dist: httpx>=0.28.1
Requires-Dist: llm>=0.26
Dynamic: license-file
